README.txt
setup.cfg
setup.py
collective/__init__.py
collective.greybox.egg-info/PKG-INFO
collective.greybox.egg-info/SOURCES.txt
collective.greybox.egg-info/dependency_links.txt
collective.greybox.egg-info/entry_points.txt
collective.greybox.egg-info/namespace_packages.txt
collective.greybox.egg-info/not-zip-safe
collective.greybox.egg-info/requires.txt
collective.greybox.egg-info/top_level.txt
collective/greybox/__init__.py
collective/greybox/configure.zcml
collective/greybox/interfaces.py
collective/greybox/version.txt
collective/greybox/browser/__init__.py
collective/greybox/browser/greybox.pt
collective/greybox/browser/greybox.py
collective/greybox/profiles/cssregistry.xml
collective/greybox/profiles/jsregistry.xml
collective/greybox/profiles/skins.xml
collective/greybox/profiles/types/Folder.xml
collective/greybox/resources/AJS.js
collective/greybox/resources/AJS_fx.js
collective/greybox/resources/__init__.py
collective/greybox/resources/g_close.gif
collective/greybox/resources/gb_scripts.js
collective/greybox/resources/gb_styles.css
collective/greybox/resources/header_bg.gif
collective/greybox/resources/indicator.gif
collective/greybox/resources/loader_frame.html
collective/greybox/resources/next.gif
collective/greybox/resources/prev.gif
collective/greybox/resources/shadowAlpha.png
collective/greybox/resources/w_close.gif
collective/greybox/skins/greybox/gb_plone.js.dtml
docs/HISTORY.txt
docs/INSTALL.txt
docs/LICENSE.GPL
docs/LICENSE.txt