Metadata-Version: 1.0
Name: collective.greybox
Version: 0.4
Summary: simple folder view using greybox
Home-page: http://www.4teamwork.ch
Author: mathias leimgruber
Author-email: info@4teamwork.ch
License: GPL
Platform: UNKNOWN
Classifier: Framework :: Plone
Classifier: Programming Language :: Python
Classifier: Topic :: Software Development :: Libraries :: Python Modules
